flow_agent_package/__init__.py
flow_agent_package/tools/__init__.py
flow_agent_package/tools/agent_tool.py
flow_agent_package/tools/constants.py
flow_agent_package/tools/contracts.py
flow_agent_package/tools/flow_manager.py
flow_agent_package/tools/memory.py
flow_agent_package/tools/orchestrator.py
flow_agent_package/tools/utils.py
flow_agent_package/tools/skill_tools/__init__.py
flow_agent_package/tools/skill_tools/flow_skill_tool.py
flow_agent_package/tools/skill_tools/index_skill_tool.py
flow_agent_package/tools/skill_tools/mir_skill_tool.py
flow_agent_package/tools/skills/__init__.py
flow_agent_package/tools/skills/agent_skill.py
flow_agent_package/tools/skills/flow_skill.py
flow_agent_package/tools/skills/index_skill.py
flow_agent_package/tools/skills/mir_skill.py
flow_agent_package/yamls/agent_tool.yaml
flow_agent_package/yamls/flow_tool.yaml
flow_agent_package/yamls/index_tool.yaml
flow_agent_package/yamls/mir_tool.yaml
flow_agent_package-0.0.39.dist-info/METADATA
flow_agent_package-0.0.39.dist-info/WHEEL
flow_agent_package-0.0.39.dist-info/entry_points.txt
flow_agent_package-0.0.39.dist-info/top_level.txt
flow_agent_package-0.0.39.dist-info/RECORD
