Metadata-Version: 2.1
Name: flow-agent-package
Version: 0.0.39
Summary: This is my agent tools package
License: UNKNOWN
Platform: UNKNOWN
Requires-Dist: semantic-kernel
Requires-Dist: keyrings.alt
Requires-Dist: azureml-rag (==0.1.24.2)
